DIAtransformers/__init__.py
DIAtransformers/models/__init__.py
DIAtransformers/models/timeSformer.py
DIAtransformers/models/vit.py
DecepticonsInAlexandria-0.0.3.dist-info/METADATA
DecepticonsInAlexandria-0.0.3.dist-info/WHEEL
DecepticonsInAlexandria-0.0.3.dist-info/top_level.txt
DecepticonsInAlexandria-0.0.3.dist-info/RECORD
