Metadata-Version: 2.1
Name: DecepticonsInAlexandria
Version: 0.0.3
Summary: A vision transformer library
Home-page: https://github.com/Lysander-curiosum/DIA
Author: Ben Irving
Author-email: irving.b@northeastern.edu
